<xc:Application class="pt::udapl::Application" instance="0" id="10" network="local" xmlns:xc="http://xdaq.web.cern.ch/xdaq/xsd/2004/XMLConfiguration-30" xmlns:xsi="http://www.w3.org/2001/XMLSchema-instance">
	<properties xmlns="urn:xdaq-application:pt::udapl::Application" xsi:type="soapenc:Struct">
		<iaName xsi:type="xsd:string">ofa-v2-ib0</iaName>
		<senderPoolSize xsi:type="xsd:unsignedInt">0x80000000</senderPoolSize>
		<receiverPoolSize xsi:type="xsd:unsignedInt">0x40000000</receiverPoolSize>
	</properties>
</xc:Application>
